stitch/__init__.py
stitch/stitch.py
Image_Stitching_Test-0.0.1.dist-info/METADATA
Image_Stitching_Test-0.0.1.dist-info/WHEEL
Image_Stitching_Test-0.0.1.dist-info/top_level.txt
Image_Stitching_Test-0.0.1.dist-info/RECORD
