Metadata-Version: 2.1
Name: Image-Stitching-Test
Version: 0.0.1
Summary: PYPI Image Stitching Test Package
Home-page: 
Author: j.Kim.vivity
Author-email: jinsu.kim@vivity.ai
Keywords: stitching test,panorama test
Classifier: Programming Language :: Python :: 3.10
Requires-Python: >=3.10
Requires-Dist: opencv-python
Requires-Dist: stitching
